dwh/__init__.py
dwh/ddl.py
dwh/exceptions.py
dwh/project.py
whlapi-0.0.1.dist-info/LICENSE
whlapi-0.0.1.dist-info/METADATA
whlapi-0.0.1.dist-info/WHEEL
whlapi-0.0.1.dist-info/top_level.txt
whlapi-0.0.1.dist-info/RECORD
